LICENSE.txt
README.md
setup.py
src/Avalara.egg-info/PKG-INFO
src/Avalara.egg-info/SOURCES.txt
src/Avalara.egg-info/dependency_links.txt
src/Avalara.egg-info/requires.txt
src/Avalara.egg-info/top_level.txt
src/avalara/__init__.py
src/avalara/_str_version.py
src/avalara/ava_logger.py
src/avalara/client.py
src/avalara/client_methods.py
src/avalara/transaction_builder.py
src/avalara/transaction_builder_methods.py
tests/test_auth.py
tests/test_basic_workflow.py
tests/test_client.py
tests/test_commit_trans.py
tests/test_create_trans.py
tests/test_ping.py
tests/test_resolve_address.py
tests/test_trans_builder.py
tests/test_void_transaction.py