Metadata-Version: 2.4
Name: Avalara
Version: 25.9.0
Summary: Avalara Tax Python SDK.
Home-page: https://github.com/avadev/AvaTax-REST-V2-Python-SDK
Author: Han Bao, Adrienne Karnoski, Robert Bronson, Philip Werner, Genevieve Conty
Author-email: han.bao@avalara.com
Classifier: Development Status :: 5 - Production/Stable
Classifier: Intended Audience :: Developers
Classifier: Programming Language :: Python :: 2.7
Classifier: Programming Language :: Python :: 3.6
License-File: LICENSE.txt
Requires-Dist: requests
Provides-Extra: test
Requires-Dist: pytest; extra == "test"
Requires-Dist: pytest-cov; extra == "test"
Requires-Dist: tox; extra == "test"
Dynamic: author
Dynamic: author-email
Dynamic: classifier
Dynamic: description
Dynamic: description-content-type
Dynamic: home-page
Dynamic: license-file
Dynamic: provides-extra
Dynamic: requires-dist
Dynamic: summary
